lightly_purple/__init__.py
lightly_purple/export_schema.py
lightly_purple/py.typed
lightly_purple/setup_logging.py
lightly_purple/type_definitions.py
lightly_purple/api/__init__.py
lightly_purple/api/app.py
lightly_purple/api/cache.py
lightly_purple/api/db.py
lightly_purple/api/db_tables.py
lightly_purple/api/features.py
lightly_purple/api/server.py
lightly_purple/api/routes/healthz.py
lightly_purple/api/routes/images.py
lightly_purple/api/routes/webapp.py
lightly_purple/api/routes/api/annotation.py
lightly_purple/api/routes/api/annotation_label.py
lightly_purple/api/routes/api/annotation_task.py
lightly_purple/api/routes/api/classifier.py
lightly_purple/api/routes/api/dataset.py
lightly_purple/api/routes/api/dataset_tag.py
lightly_purple/api/routes/api/exceptions.py
lightly_purple/api/routes/api/features.py
lightly_purple/api/routes/api/metadata.py
lightly_purple/api/routes/api/metrics.py
lightly_purple/api/routes/api/sample.py
lightly_purple/api/routes/api/settings.py
lightly_purple/api/routes/api/status.py
lightly_purple/api/routes/api/text_embedding.py
lightly_purple/api/routes/api/validators.py
lightly_purple/dataset/__init__.py
lightly_purple/dataset/edge_embedding_generator.py
lightly_purple/dataset/embedding_generator.py
lightly_purple/dataset/embedding_manager.py
lightly_purple/dataset/env.py
lightly_purple/dataset/file_utils.py
lightly_purple/dataset/loader.py
lightly_purple/dataset/mobileclip_embedding_generator.py
lightly_purple/dist-purple-view-app/apple-touch-icon-precomposed.png
lightly_purple/dist-purple-view-app/apple-touch-icon.png
lightly_purple/dist-purple-view-app/favicon.png
lightly_purple/dist-purple-view-app/index.html
lightly_purple/dist-purple-view-app/_app/env.js
lightly_purple/dist-purple-view-app/_app/version.json
lightly_purple/dist-purple-view-app/_app/immutable/assets/0.DLnHK0Fn.css
lightly_purple/dist-purple-view-app/_app/immutable/assets/LightlyLogo.BNjCIww-.png
lightly_purple-0.3.0.dist-info/METADATA
lightly_purple-0.3.0.dist-info/WHEEL
lightly_purple-0.3.0.dist-info/RECORD
