Metadata-Version: 2.4
Name: lightly-purple
Version: 0.3.0
Summary: Lightly Purple is a lightweight, fast, and easy-to-use data exploration tool for data scientists and engineers.
Classifier: Operating System :: MacOS :: MacOS X
Classifier: Operating System :: Microsoft :: Windows
Classifier: Operating System :: POSIX :: Linux
Classifier: Programming Language :: Python :: 3
Classifier: Programming Language :: Python :: 3.8
Classifier: Programming Language :: Python :: 3.9
Classifier: Programming Language :: Python :: 3.10
Classifier: Programming Language :: Python :: 3.11
Requires-Python: >=3.8
Requires-Dist: annotated-types==0.7.0
Requires-Dist: duckdb-engine>=0.13.5
Requires-Dist: duckdb>=1.1.3
Requires-Dist: environs<12.0.0
Requires-Dist: eval-type-backport>=0.2.2
Requires-Dist: fastapi>=0.115.5
Requires-Dist: faster-coco-eval>=1.6.5
Requires-Dist: labelformat>=0.1.7
Requires-Dist: lightly-mundig==0.1.3
Requires-Dist: open-clip-torch>=2.20.0
Requires-Dist: python-multipart>=0.0.20
Requires-Dist: scikit-learn==1.3.2
Requires-Dist: sqlmodel>=0.0.22
Requires-Dist: torchmetrics>=1.5.2
Requires-Dist: tqdm>=4.65.0
Requires-Dist: typing-extensions>=4.12.2
Requires-Dist: uvicorn>=0.32.1
Requires-Dist: xxhash>=3.5.0
